{
  "name": "Superfluid Token List B",
  "version": {
    "major": 2,
    "minor": 3,
    "patch": 0
  },
  "timestamp": "2023-10-09T11:39:20.594Z",
  "tokens": [
    {
      "address": "0x6af916e2001bc4935e6d2f256363ed54eb8e20e0",
      "name": "Super EUROe Stablecoin",
      "symbol": "EUROex",
      "decimals": 18,
      "chainId": 43114,
      "extensions": {
        "superTokenInfo": {
          "type": "Wrapper",
          "underlyingTokenAddress": "0x820802fa8a99901f52e39acd21177b0be6ee2974"
        }
      },
      "logoURI": "https://raw.githubusercontent.com/superfluid-finance/assets/master/public/tokens/euroe/icon.svg",
      "tags": ["supertoken", "tier_b"]
    },
    {
      "address": "0x820802fa8a99901f52e39acd21177b0be6ee2974",
      "name": "EUROe Stablecoin",
      "symbol": "EUROe",
      "decimals": 6,
      "chainId": 43114,
      "logoURI": "https://raw.githubusercontent.com/superfluid-finance/assets/master/public/tokens/euroe/icon.svg",
      "tags": ["underlying"]
    },
    {
      "address": "0xbd80cfa9d93a87d1bb895f810ea348e496611cd4",
      "name": "Own a fraction",
      "symbol": "FRACTION",
      "decimals": 18,
      "chainId": 43114,
      "extensions": {
        "superTokenInfo": {
          "type": "Pure"
        }
      },
      "logoURI": "https://raw.githubusercontent.com/superfluid-finance/assets/master/public/tokens/fraction/icon.svg",
      "tags": ["supertoken", "tier_b"]
    },
    {
      "address": "0x2bf2ba13735160624a0feae98f6ac8f70885ea61",
      "name": "Own a fraction",
      "symbol": "FRACTION",
      "decimals": 18,
      "chainId": 42161,
      "extensions": {
        "superTokenInfo": {
          "type": "Pure"
        }
      },
      "logoURI": "https://raw.githubusercontent.com/superfluid-finance/assets/master/public/tokens/fraction/icon.svg",
      "tags": ["supertoken", "tier_b"]
    },
    {
      "address": "0x95f1ee4cb6dc16136a79d367a010add361e5192c",
      "name": "Super EUROe Stablecoin",
      "symbol": "EUROex",
      "decimals": 18,
      "chainId": 42161,
      "extensions": {
        "superTokenInfo": {
          "type": "Wrapper",
          "underlyingTokenAddress": "0xcf985aba4647a432e60efceeb8054bbd64244305"
        }
      },
      "logoURI": "https://raw.githubusercontent.com/superfluid-finance/assets/master/public/tokens/euroe/icon.svg",
      "tags": ["supertoken", "tier_b"]
    },
    {
      "address": "0xcf985aba4647a432e60efceeb8054bbd64244305",
      "name": "EUROe Stablecoin",
      "symbol": "EUROe",
      "decimals": 6,
      "chainId": 42161,
      "logoURI": "https://raw.githubusercontent.com/superfluid-finance/assets/master/public/tokens/euroe/icon.svg",
      "tags": ["underlying"]
    },
    {
      "address": "0xefa54be8d63fd0d95edd7965d0bd7477c33995a8",
      "name": "Super Rocket Pool Protocol",
      "symbol": "RPLx",
      "decimals": 18,
      "chainId": 42161,
      "extensions": {
        "superTokenInfo": {
          "type": "Wrapper",
          "underlyingTokenAddress": "0xb766039cc6db368759c1e56b79affe831d0cc507"
        }
      },
      "logoURI": "https://raw.githubusercontent.com/superfluid-finance/assets/master/public/tokens/rpl/icon.png",
      "tags": ["supertoken", "tier_b"]
    },
    {
      "address": "0xb766039cc6db368759c1e56b79affe831d0cc507",
      "name": "Rocket Pool Protocol",
      "symbol": "RPL",
      "decimals": 18,
      "chainId": 42161,
      "logoURI": "https://raw.githubusercontent.com/superfluid-finance/assets/master/public/tokens/rpl/icon.png",
      "tags": ["underlying"]
    },
    {
      "address": "0x744786ab00ed5a0b77ca754eb6f3ec0607c7fa79",
      "name": "Super Hey Reborn",
      "symbol": "RBx",
      "decimals": 18,
      "chainId": 56,
      "extensions": {
        "superTokenInfo": {
          "type": "Wrapper",
          "underlyingTokenAddress": "0x441bb79f2da0daf457bad3d401edb68535fb3faa"
        }
      },
      "logoURI": "https://raw.githubusercontent.com/superfluid-finance/assets/master/public/tokens/rb/icon.png",
      "tags": ["supertoken", "tier_b"]
    },
    {
      "address": "0x441bb79f2da0daf457bad3d401edb68535fb3faa",
      "name": "Hey Reborn",
      "symbol": "RB",
      "decimals": 18,
      "chainId": 56,
      "logoURI": "https://raw.githubusercontent.com/superfluid-finance/assets/master/public/tokens/rb/icon.png",
      "tags": ["underlying"]
    },
    {
      "address": "0xbd80cfa9d93a87d1bb895f810ea348e496611cd4",
      "name": "Own a fraction",
      "symbol": "FRACTION",
      "decimals": 18,
      "chainId": 56,
      "extensions": {
        "superTokenInfo": {
          "type": "Pure"
        }
      },
      "logoURI": "https://raw.githubusercontent.com/superfluid-finance/assets/master/public/tokens/fraction/icon.svg",
      "tags": ["supertoken", "tier_b"]
    },
    {
      "address": "0x62b8b11039fcfe5ab0c56e502b1c372a3d2a9c7a",
      "name": "GoodDollar",
      "symbol": "G$",
      "decimals": 18,
      "chainId": 42220,
      "extensions": {
        "superTokenInfo": {
          "type": "Pure"
        }
      },
      "logoURI": "https://raw.githubusercontent.com/superfluid-finance/assets/master/public/tokens/g$/icon.png",
      "tags": ["supertoken", "tier_b"]
    },
    {
      "address": "0x2bf2ba13735160624a0feae98f6ac8f70885ea61",
      "name": "Own a fraction",
      "symbol": "FRACTION",
      "decimals": 18,
      "chainId": 100,
      "extensions": {
        "superTokenInfo": {
          "type": "Pure"
        }
      },
      "logoURI": "https://raw.githubusercontent.com/superfluid-finance/assets/master/public/tokens/fraction/icon.svg",
      "tags": ["supertoken", "tier_b"]
    },
    {
      "address": "0x63e62989d9eb2d37dfdb1f93a22f063635b07d51",
      "name": "Minerva Wallet SuperToken",
      "symbol": "MIVA",
      "decimals": 18,
      "chainId": 100,
      "extensions": {
        "superTokenInfo": {
          "type": "Pure"
        }
      },
      "logoURI": "https://raw.githubusercontent.com/superfluid-finance/assets/master/public/tokens/miva/icon.svg",
      "tags": ["supertoken", "tier_b"]
    },
    {
      "address": "0xac945dc430cef2bb8fb78b3cb5fbc936dd2c8ab6",
      "name": "Super CoW Protocol Token from Mainnet",
      "symbol": "COWx",
      "decimals": 18,
      "chainId": 100,
      "extensions": {
        "superTokenInfo": {
          "type": "Wrapper",
          "underlyingTokenAddress": "0x177127622c4a00f3d409b75571e12cb3c8973d3c"
        }
      },
      "logoURI": "https://raw.githubusercontent.com/superfluid-finance/assets/master/public/tokens/cow/icon.svg",
      "tags": ["supertoken", "tier_b"]
    },
    {
      "address": "0x177127622c4a00f3d409b75571e12cb3c8973d3c",
      "name": "CoW Protocol Token from Mainnet",
      "symbol": "COW",
      "decimals": 18,
      "chainId": 100,
      "logoURI": "https://raw.githubusercontent.com/superfluid-finance/assets/master/public/tokens/cow/icon.svg",
      "tags": ["underlying"]
    },
    {
      "address": "0xc0712524b39323eb2437e69226b261d928629dc8",
      "name": "Super Honey",
      "symbol": "HNYx",
      "decimals": 18,
      "chainId": 100,
      "extensions": {
        "superTokenInfo": {
          "type": "Wrapper",
          "underlyingTokenAddress": "0x71850b7e9ee3f13ab46d67167341e4bdc905eef9"
        }
      },
      "logoURI": "https://raw.githubusercontent.com/superfluid-finance/assets/master/public/tokens/hny/icon.png",
      "tags": ["supertoken", "tier_b"]
    },
    {
      "address": "0x71850b7e9ee3f13ab46d67167341e4bdc905eef9",
      "name": "Honey",
      "symbol": "HNY",
      "decimals": 18,
      "chainId": 100,
      "logoURI": "https://raw.githubusercontent.com/superfluid-finance/assets/master/public/tokens/hny/icon.png",
      "tags": ["underlying"]
    },
    {
      "address": "0x8f6f22a962899ade3c46627df45d4a05622cebf2",
      "name": "Super Swivel Governance Token",
      "symbol": "SWIVx",
      "decimals": 18,
      "chainId": 1,
      "extensions": {
        "superTokenInfo": {
          "type": "Wrapper",
          "underlyingTokenAddress": "0xbf30461210b37012783957d90dc26b95ce3b6f2d"
        }
      },
      "logoURI": "https://raw.githubusercontent.com/superfluid-finance/assets/master/public/tokens/swiv/icon.svg",
      "tags": ["supertoken", "tier_b"]
    },
    {
      "address": "0xbf30461210b37012783957d90dc26b95ce3b6f2d",
      "name": "Swivel Governance Token",
      "symbol": "SWIV",
      "decimals": 18,
      "chainId": 1,
      "logoURI": "https://raw.githubusercontent.com/superfluid-finance/assets/master/public/tokens/swiv/icon.svg",
      "tags": ["underlying"]
    },
    {
      "address": "0xd70408b34ed121722631d647d37c4e6641ec363d",
      "name": "Super Aragon Network Token",
      "symbol": "ANTx",
      "decimals": 18,
      "chainId": 1,
      "extensions": {
        "superTokenInfo": {
          "type": "Wrapper",
          "underlyingTokenAddress": "0xa117000000f279d81a1d3cc75430faa017fa5a2e"
        }
      },
      "logoURI": "https://raw.githubusercontent.com/superfluid-finance/assets/master/public/tokens/ant/icon.svg",
      "tags": ["supertoken", "tier_b"]
    },
    {
      "address": "0xa117000000f279d81a1d3cc75430faa017fa5a2e",
      "name": "Aragon Network Token",
      "symbol": "ANT",
      "decimals": 18,
      "chainId": 1,
      "logoURI": "https://raw.githubusercontent.com/superfluid-finance/assets/master/public/tokens/ant/icon.svg",
      "tags": ["underlying"]
    },
    {
      "address": "0x167832baf36d1ac0af9e8d8ad329fa418bed5cd9",
      "name": "ABToken",
      "symbol": "ABT",
      "decimals": 18,
      "chainId": 10,
      "extensions": {
        "superTokenInfo": {
          "type": "Pure"
        }
      },
      "logoURI": "https://raw.githubusercontent.com/superfluid-finance/assets/master/public/tokens/abt/icon.svg",
      "tags": ["supertoken", "tier_b"]
    },
    {
      "address": "0x1828bff08bd244f7990eddcd9b19cc654b33cdb4",
      "name": "Super Optimism",
      "symbol": "OPx",
      "decimals": 18,
      "chainId": 10,
      "extensions": {
        "superTokenInfo": {
          "type": "Wrapper",
          "underlyingTokenAddress": "0x4200000000000000000000000000000000000042"
        }
      },
      "logoURI": "https://raw.githubusercontent.com/superfluid-finance/assets/master/public/tokens/op/icon.svg",
      "tags": ["supertoken", "tier_b"]
    },
    {
      "address": "0x4200000000000000000000000000000000000042",
      "name": "Optimism",
      "symbol": "OP",
      "decimals": 18,
      "chainId": 10,
      "logoURI": "https://raw.githubusercontent.com/superfluid-finance/assets/master/public/tokens/op/icon.svg",
      "tags": ["underlying"]
    },
    {
      "address": "0x4caB5B9930210E2EdC6A905B9C75D615872A1A7E",
      "name": "Super Giveth Token",
      "symbol": "GIVx",
      "decimals": 18,
      "chainId": 10,
      "extensions": {
        "superTokenInfo": {
          "type": "Wrapper",
          "underlyingTokenAddress": "0x528CDc92eAB044E1E39FE43B9514bfdAB4412B98"
        }
      },
      "logoURI": "https://raw.githubusercontent.com/Giveth/giveth-design-assets/9fc25bfcd4a04cae53ceaecb8f96e5db738ff8a5/02-logos/GIV%20Token/GIVToken_128x128.svg",
      "tags": ["supertoken", "tier_b"]
    },
    {
      "address": "0x528CDc92eAB044E1E39FE43B9514bfdAB4412B98",
      "name": "Giveth Token",
      "symbol": "GIV",
      "decimals": 18,
      "chainId": 10,
      "logoURI": "https://raw.githubusercontent.com/Giveth/giveth-design-assets/9fc25bfcd4a04cae53ceaecb8f96e5db738ff8a5/02-logos/GIV%20Token/GIVToken_128x128.svg",
      "tags": ["underlying"]
    },
    {
      "address": "0x02ef6868d69707b6093a2962bb5fe5661fcc0deb",
      "name": "Super STASIS EURS",
      "symbol": "EURSx",
      "decimals": 18,
      "chainId": 137,
      "extensions": {
        "superTokenInfo": {
          "type": "Wrapper",
          "underlyingTokenAddress": "0xe111178a87a3bff0c8d18decba5798827539ae99"
        }
      },
      "logoURI": "https://raw.githubusercontent.com/superfluid-finance/assets/master/public/tokens/eurs/icon.png",
      "tags": ["supertoken", "tier_b"]
    },
    {
      "address": "0xe111178a87a3bff0c8d18decba5798827539ae99",
      "name": "STASIS EURS Token (PoS)",
      "symbol": "EURS",
      "decimals": 2,
      "chainId": 137,
      "logoURI": "https://raw.githubusercontent.com/superfluid-finance/assets/master/public/tokens/eurs/icon.png",
      "tags": ["underlying"]
    },
    {
      "address": "0x094ed09f072596c34c5c0b197dceb0da6b04c580",
      "name": "Super NEAR",
      "symbol": "NEARx",
      "decimals": 18,
      "chainId": 137,
      "extensions": {
        "superTokenInfo": {
          "type": "Wrapper",
          "underlyingTokenAddress": "0x72bd80445b0db58ebe3e8db056529d4c5faf6f2f"
        }
      },
      "logoURI": "https://raw.githubusercontent.com/superfluid-finance/assets/master/public/tokens/near/icon.png",
      "tags": ["supertoken", "tier_b"]
    },
    {
      "address": "0x72bd80445b0db58ebe3e8db056529d4c5faf6f2f",
      "name": "NEAR",
      "symbol": "NEAR",
      "decimals": 18,
      "chainId": 137,
      "logoURI": "https://raw.githubusercontent.com/superfluid-finance/assets/master/public/tokens/near/icon.png",
      "tags": ["underlying"]
    },
    {
      "address": "0x12c294107772b10815307c05989dabd71c21670e",
      "name": "Stake DAO Token (PoS)",
      "symbol": "SDTx",
      "decimals": 18,
      "chainId": 137,
      "extensions": {
        "superTokenInfo": {
          "type": "Wrapper",
          "underlyingTokenAddress": "0x361a5a4993493ce00f61c32d4ecca5512b82ce90"
        }
      },
      "logoURI": "https://raw.githubusercontent.com/superfluid-finance/assets/master/public/tokens/sdt/icon.jpg",
      "tags": ["supertoken", "tier_b"]
    },
    {
      "address": "0x361a5a4993493ce00f61c32d4ecca5512b82ce90",
      "name": "Stake DAO Token (PoS)",
      "symbol": "SDT",
      "decimals": 18,
      "chainId": 137,
      "logoURI": "https://raw.githubusercontent.com/superfluid-finance/assets/master/public/tokens/sdt/icon.jpg",
      "tags": ["underlying"]
    },
    {
      "address": "0x1adca32b906883e474aebcba5708b41f3645f941",
      "name": "SuperMOCA",
      "symbol": "MOCAx",
      "decimals": 18,
      "chainId": 137,
      "extensions": {
        "superTokenInfo": {
          "type": "Wrapper",
          "underlyingTokenAddress": "0xce899f26928a2b21c6a2fddd393ef37c61dba918"
        }
      },
      "logoURI": "https://raw.githubusercontent.com/superfluid-finance/assets/master/public/tokens/moca/icon.jpeg",
      "tags": ["supertoken", "tier_b"]
    },
    {
      "address": "0xce899f26928a2b21c6a2fddd393ef37c61dba918",
      "name": "Museum of Crypto Art",
      "symbol": "MOCA",
      "decimals": 18,
      "chainId": 137,
      "logoURI": "https://raw.githubusercontent.com/superfluid-finance/assets/master/public/tokens/moca/icon.jpeg",
      "tags": ["underlying"]
    },
    {
      "address": "0x1bd951a9c9a5ec665abef684425f025dc8738cca",
      "name": "Super Seed (PoS)",
      "symbol": "SEEDx",
      "decimals": 18,
      "chainId": 137,
      "extensions": {
        "superTokenInfo": {
          "type": "Wrapper",
          "underlyingTokenAddress": "0xeaecc18198a475c921b24b8a6c1c1f0f5f3f7ea0"
        }
      },
      "logoURI": "https://raw.githubusercontent.com/superfluid-finance/assets/master/public/tokens/seed/icon.png",
      "tags": ["supertoken", "tier_b"]
    },
    {
      "address": "0xeaecc18198a475c921b24b8a6c1c1f0f5f3f7ea0",
      "name": "Seed (PoS)",
      "symbol": "SEED",
      "decimals": 18,
      "chainId": 137,
      "logoURI": "https://raw.githubusercontent.com/superfluid-finance/assets/master/public/tokens/seed/icon.png",
      "tags": ["underlying"]
    },
    {
      "address": "0x229c5d13452dc302499b5c113768a0db0c9d5c05",
      "name": "Super BlackPool Token (PoS)",
      "symbol": "BPTx",
      "decimals": 18,
      "chainId": 137,
      "extensions": {
        "superTokenInfo": {
          "type": "Wrapper",
          "underlyingTokenAddress": "0x6863bd30c9e313b264657b107352ba246f8af8e0"
        }
      },
      "logoURI": "https://raw.githubusercontent.com/superfluid-finance/assets/master/public/tokens/bpt/icon.svg",
      "tags": ["supertoken", "tier_b"]
    },
    {
      "address": "0x6863bd30c9e313b264657b107352ba246f8af8e0",
      "name": "BlackPool Token (PoS)",
      "symbol": "BPT",
      "decimals": 18,
      "chainId": 137,
      "logoURI": "https://raw.githubusercontent.com/superfluid-finance/assets/master/public/tokens/bpt/icon.svg",
      "tags": ["underlying"]
    },
    {
      "address": "0x263026e7e53dbfdce5ae55ade22493f828922965",
      "name": "Ricochet",
      "symbol": "RIC",
      "decimals": 18,
      "chainId": 137,
      "extensions": {
        "superTokenInfo": {
          "type": "Pure"
        }
      },
      "logoURI": "https://raw.githubusercontent.com/superfluid-finance/assets/master/public/tokens/ric/icon.svg",
      "tags": ["supertoken", "tier_b"]
    },
    {
      "address": "0x2b47ee85a85b18be029af94df52fcb52c54725f4",
      "name": "superSTAK ",
      "symbol": "STAKx",
      "decimals": 18,
      "chainId": 137,
      "extensions": {
        "superTokenInfo": {
          "type": "Wrapper",
          "underlyingTokenAddress": "0x46a5d492788f8afdfc743ab7d7bd13f996249ed5"
        }
      },
      "logoURI": "https://raw.githubusercontent.com/superfluid-finance/assets/master/public/tokens/stak/icon.png",
      "tags": ["supertoken", "tier_b"]
    },
    {
      "address": "0x46a5d492788f8afdfc743ab7d7bd13f996249ed5",
      "name": "Jigstack (PoS)",
      "symbol": "STAK",
      "decimals": 18,
      "chainId": 137,
      "logoURI": "https://raw.githubusercontent.com/superfluid-finance/assets/master/public/tokens/stak/icon.png",
      "tags": ["underlying"]
    },
    {
      "address": "0x2c530af1f088b836fa0dca23c7ea50e669508c4c",
      "name": "Super MAKER (PoS)",
      "symbol": "MKRx",
      "decimals": 18,
      "chainId": 137,
      "extensions": {
        "superTokenInfo": {
          "type": "Wrapper",
          "underlyingTokenAddress": "0x6f7c932e7684666c9fd1d44527765433e01ff61d"
        }
      },
      "logoURI": "https://raw.githubusercontent.com/superfluid-finance/assets/master/public/tokens/mkr/icon.svg",
      "tags": ["supertoken", "tier_b"]
    },
    {
      "address": "0x6f7c932e7684666c9fd1d44527765433e01ff61d",
      "name": "MAKER (PoS)",
      "symbol": "MKR",
      "decimals": 18,
      "chainId": 137,
      "logoURI": "https://raw.githubusercontent.com/superfluid-finance/assets/master/public/tokens/mkr/icon.svg",
      "tags": ["underlying"]
    },
    {
      "address": "0x2d4dc956fbd0044a4eba945e8bbaf98a14025c2d",
      "name": "Streaming IbAlluo ETH",
      "symbol": "StIbAlluoEth",
      "decimals": 18,
      "chainId": 137,
      "extensions": {
        "superTokenInfo": {
          "type": "Wrapper",
          "underlyingTokenAddress": "0xc677b0918a96ad258a68785c2a3955428dea7e50"
        }
      },
      "logoURI": "https://raw.githubusercontent.com/superfluid-finance/assets/master/public/tokens/iballuoeth/icon.svg",
      "tags": ["supertoken", "tier_b"]
    },
    {
      "address": "0xc677b0918a96ad258a68785c2a3955428dea7e50",
      "name": "Interest Bearing Alluo ETH",
      "symbol": "IbAlluoETH",
      "decimals": 18,
      "chainId": 137,
      "logoURI": "https://raw.githubusercontent.com/superfluid-finance/assets/master/public/tokens/iballuoeth/icon.svg",
      "tags": ["underlying"]
    },
    {
      "address": "0x3038b359240dff5ccd42dffd21f12b428034be38",
      "name": "Super agEUR",
      "symbol": "agEURx",
      "decimals": 18,
      "chainId": 137,
      "extensions": {
        "superTokenInfo": {
          "type": "Wrapper",
          "underlyingTokenAddress": "0xe0b52e49357fd4daf2c15e02058dce6bc0057db4"
        }
      },
      "logoURI": "https://raw.githubusercontent.com/superfluid-finance/assets/master/public/tokens/ageur/icon.png",
      "tags": ["supertoken", "tier_b"]
    },
    {
      "address": "0xe0b52e49357fd4daf2c15e02058dce6bc0057db4",
      "name": "agEUR",
      "symbol": "agEUR",
      "decimals": 18,
      "chainId": 137,
      "logoURI": "https://raw.githubusercontent.com/superfluid-finance/assets/master/public/tokens/ageur/icon.png",
      "tags": ["underlying"]
    },
    {
      "address": "0x32cefdf2b3df73bdebaa7cd3b0135b3a79d28dcc",
      "name": "Super Request Token",
      "symbol": "REQx",
      "decimals": 18,
      "chainId": 137,
      "extensions": {
        "superTokenInfo": {
          "type": "Wrapper",
          "underlyingTokenAddress": "0xb25e20de2f2ebb4cffd4d16a55c7b395e8a94762"
        }
      },
      "logoURI": "https://raw.githubusercontent.com/superfluid-finance/assets/master/public/tokens/req/icon.svg",
      "tags": ["supertoken", "tier_b"]
    },
    {
      "address": "0xb25e20de2f2ebb4cffd4d16a55c7b395e8a94762",
      "name": "Request",
      "symbol": "REQ",
      "decimals": 18,
      "chainId": 137,
      "logoURI": "https://raw.githubusercontent.com/superfluid-finance/assets/master/public/tokens/req/icon.svg",
      "tags": ["underlying"]
    },
    {
      "address": "0x3e70e15c189e1ffe8ff44d713605528dc1701b63",
      "name": "Streaming IbAlluo BTC",
      "symbol": "StIbAlluoBTC",
      "decimals": 18,
      "chainId": 137,
      "extensions": {
        "superTokenInfo": {
          "type": "Wrapper",
          "underlyingTokenAddress": "0xf272ff86c86529504f0d074b210e95fc4cfcdce2"
        }
      },
      "logoURI": "https://raw.githubusercontent.com/superfluid-finance/assets/master/public/tokens/iballuobtc/icon.svg",
      "tags": ["supertoken", "tier_b"]
    },
    {
      "address": "0xf272ff86c86529504f0d074b210e95fc4cfcdce2",
      "name": "Interest Bearing Alluo BTC",
      "symbol": "IbAlluoBTC",
      "decimals": 18,
      "chainId": 137,
      "logoURI": "https://raw.githubusercontent.com/superfluid-finance/assets/master/public/tokens/iballuobtc/icon.svg",
      "tags": ["underlying"]
    },
    {
      "address": "0x49765f8fcf0a1cd4f98da906f0974a9085d43e51",
      "name": "Super XSGD",
      "symbol": "XSGDx",
      "decimals": 18,
      "chainId": 137,
      "extensions": {
        "superTokenInfo": {
          "type": "Wrapper",
          "underlyingTokenAddress": "0xdc3326e71d45186f113a2f448984ca0e8d201995"
        }
      },
      "tags": ["supertoken", "tier_b"]
    },
    {
      "address": "0xdc3326e71d45186f113a2f448984ca0e8d201995",
      "name": "XSGD",
      "symbol": "XSGD",
      "decimals": 6,
      "chainId": 137,
      "tags": ["underlying"]
    },
    {
      "address": "0x4bde23854e7c81218463f6c8f331b46144e98eac",
      "name": "Super jEUR",
      "symbol": "jEURx",
      "decimals": 18,
      "chainId": 137,
      "extensions": {
        "superTokenInfo": {
          "type": "Wrapper",
          "underlyingTokenAddress": "0x4e3decbb3645551b8a19f0ea1678079fcb33fb4c"
        }
      },
      "logoURI": "https://raw.githubusercontent.com/superfluid-finance/assets/master/public/tokens/jeur/icon.svg",
      "tags": ["supertoken", "tier_b"]
    },
    {
      "address": "0x4e3decbb3645551b8a19f0ea1678079fcb33fb4c",
      "name": "Jarvis Synthetic Euro",
      "symbol": "jEUR",
      "decimals": 18,
      "chainId": 137,
      "logoURI": "https://raw.githubusercontent.com/superfluid-finance/assets/master/public/tokens/jeur/icon.svg",
      "tags": ["underlying"]
    },
    {
      "address": "0x5d6fdc854b46e8b237bd2ccc2714cfa3d18cf58e",
      "name": "Super Alongside Crypto Market Index",
      "symbol": "AMKTx",
      "decimals": 18,
      "chainId": 137,
      "extensions": {
        "superTokenInfo": {
          "type": "Wrapper",
          "underlyingTokenAddress": "0xb87904db461005fc716a6bf9f2d451c33b10b80b"
        }
      },
      "logoURI": "https://raw.githubusercontent.com/superfluid-finance/assets/master/public/tokens/amkt/icon.png",
      "tags": ["supertoken", "tier_b"]
    },
    {
      "address": "0xb87904db461005fc716a6bf9f2d451c33b10b80b",
      "name": "Alongside Crypto Market Index (PoS)",
      "symbol": "AMKT",
      "decimals": 18,
      "chainId": 137,
      "logoURI": "https://raw.githubusercontent.com/superfluid-finance/assets/master/public/tokens/amkt/icon.png",
      "tags": ["underlying"]
    },
    {
      "address": "0x5e31d5bdd6c87edff8659d9ead9ce0013fb47184",
      "name": "Super EUROe Stablecoin",
      "symbol": "EUROex",
      "decimals": 18,
      "chainId": 137,
      "extensions": {
        "superTokenInfo": {
          "type": "Wrapper",
          "underlyingTokenAddress": "0x820802fa8a99901f52e39acd21177b0be6ee2974"
        }
      },
      "logoURI": "https://raw.githubusercontent.com/superfluid-finance/assets/master/public/tokens/euroe/icon.svg",
      "tags": ["supertoken", "tier_b"]
    },
    {
      "address": "0x820802fa8a99901f52e39acd21177b0be6ee2974",
      "name": "EUROe Stablecoin",
      "symbol": "EUROe",
      "decimals": 6,
      "chainId": 137,
      "logoURI": "https://raw.githubusercontent.com/superfluid-finance/assets/master/public/tokens/euroe/icon.svg",
      "tags": ["underlying"]
    },
    {
      "address": "0x6328c1c2e258a314bdac5227e9c7d212312297ad",
      "name": "Super jGBP",
      "symbol": "jGBPx",
      "decimals": 18,
      "chainId": 137,
      "extensions": {
        "superTokenInfo": {
          "type": "Wrapper",
          "underlyingTokenAddress": "0x767058f11800fba6a682e73a6e79ec5eb74fac8c"
        }
      },
      "logoURI": "https://raw.githubusercontent.com/superfluid-finance/assets/master/public/tokens/jgbp/icon.png",
      "tags": ["supertoken", "tier_b"]
    },
    {
      "address": "0x767058f11800fba6a682e73a6e79ec5eb74fac8c",
      "name": "Jarvis Synthetic British Pound",
      "symbol": "jGBP",
      "decimals": 18,
      "chainId": 137,
      "logoURI": "https://raw.githubusercontent.com/superfluid-finance/assets/master/public/tokens/jgbp/icon.png",
      "tags": ["underlying"]
    },
    {
      "address": "0x64059efad287b57d8df9c313d56f6c1a5c945b94",
      "name": "Super jMXN",
      "symbol": "jMXNx",
      "decimals": 18,
      "chainId": 137,
      "extensions": {
        "superTokenInfo": {
          "type": "Wrapper",
          "underlyingTokenAddress": "0xbd1fe73e1f12bd2bc237de9b626f056f21f86427"
        }
      },
      "logoURI": "https://raw.githubusercontent.com/superfluid-finance/assets/master/public/tokens/jmxn/icon.svg",
      "tags": ["supertoken", "tier_b"]
    },
    {
      "address": "0xbd1fe73e1f12bd2bc237de9b626f056f21f86427",
      "name": "Jarvis Synthetic Mexican Peso",
      "symbol": "jMXN",
      "decimals": 18,
      "chainId": 137,
      "logoURI": "https://raw.githubusercontent.com/superfluid-finance/assets/master/public/tokens/jmxn/icon.svg",
      "tags": ["underlying"]
    },
    {
      "address": "0x673d41ebc2b499d3545e5a0309124cd94eda3fb0",
      "name": "Super Slingshot",
      "symbol": "SLINGx",
      "decimals": 18,
      "chainId": 137,
      "extensions": {
        "superTokenInfo": {
          "type": "Wrapper",
          "underlyingTokenAddress": "0xfc9fa9771145fbb98d15c8c2cc94b837a56d554c"
        }
      },
      "logoURI": "https://raw.githubusercontent.com/superfluid-finance/assets/master/public/tokens/sling/icon.png",
      "tags": ["supertoken", "tier_b"]
    },
    {
      "address": "0xfc9fa9771145fbb98d15c8c2cc94b837a56d554c",
      "name": "Slingshot",
      "symbol": "SLING",
      "decimals": 18,
      "chainId": 137,
      "logoURI": "https://raw.githubusercontent.com/superfluid-finance/assets/master/public/tokens/sling/icon.png",
      "tags": ["underlying"]
    },
    {
      "address": "0x72a9bae5ce6de9816aadcbc24daa09f5d169a980",
      "name": "Monerium EUR emoney",
      "symbol": "EURex",
      "decimals": 18,
      "chainId": 137,
      "extensions": {
        "superTokenInfo": {
          "type": "Wrapper",
          "underlyingTokenAddress": "0x18ec0a6e18e5bc3784fdd3a3634b31245ab704f6"
        }
      },
      "logoURI": "https://raw.githubusercontent.com/superfluid-finance/assets/master/public/tokens/eure/icon.svg",
      "tags": ["supertoken", "tier_b"]
    },
    {
      "address": "0x18ec0a6e18e5bc3784fdd3a3634b31245ab704f6",
      "name": "Monerium EUR emoney",
      "symbol": "EURe",
      "decimals": 18,
      "chainId": 137,
      "logoURI": "https://raw.githubusercontent.com/superfluid-finance/assets/master/public/tokens/eure/icon.svg",
      "tags": ["underlying"]
    },
    {
      "address": "0x782b2725593b18c8453568f3ffb2645b6cb5033e",
      "name": "Super jCAD",
      "symbol": "jCADx",
      "decimals": 18,
      "chainId": 137,
      "extensions": {
        "superTokenInfo": {
          "type": "Wrapper",
          "underlyingTokenAddress": "0x8ca194a3b22077359b5732de53373d4afc11dee3"
        }
      },
      "logoURI": "https://raw.githubusercontent.com/superfluid-finance/assets/master/public/tokens/jcad/icon.png",
      "tags": ["supertoken", "tier_b"]
    },
    {
      "address": "0x8ca194a3b22077359b5732de53373d4afc11dee3",
      "name": "Jarvis Synthetic Canadian Dollar",
      "symbol": "jCAD",
      "decimals": 18,
      "chainId": 137,
      "logoURI": "https://raw.githubusercontent.com/superfluid-finance/assets/master/public/tokens/jcad/icon.png",
      "tags": ["underlying"]
    },
    {
      "address": "0x7893304db2c9e5dab18fd5b41855ea5a40fb070d",
      "name": "Super jBGN",
      "symbol": "jBGNx",
      "decimals": 18,
      "chainId": 137,
      "extensions": {
        "superTokenInfo": {
          "type": "Wrapper",
          "underlyingTokenAddress": "0x60e91fc3a60362ca44aea0263dbc4b96302f6ade"
        }
      },
      "logoURI": "https://raw.githubusercontent.com/superfluid-finance/assets/master/public/tokens/jbgn/icon.png",
      "tags": ["supertoken", "tier_b"]
    },
    {
      "address": "0x60e91fc3a60362ca44aea0263dbc4b96302f6ade",
      "name": "Jarvis Synthetic Bulgarian Lev",
      "symbol": "jBGN",
      "decimals": 18,
      "chainId": 137,
      "logoURI": "https://raw.githubusercontent.com/superfluid-finance/assets/master/public/tokens/jbgn/icon.png",
      "tags": ["underlying"]
    },
    {
      "address": "0x7d35eab5f5fdf6b458b18c29d0d61092835f9e99",
      "name": "Super Signal Token",
      "symbol": "SIGNALx",
      "decimals": 18,
      "chainId": 137,
      "extensions": {
        "superTokenInfo": {
          "type": "Wrapper",
          "underlyingTokenAddress": "0x9b532ffa57631d77163be75e965e6adfc3b81510"
        }
      },
      "tags": ["supertoken", "tier_b"]
    },
    {
      "address": "0x9b532ffa57631d77163be75e965e6adfc3b81510",
      "name": "RADAR",
      "symbol": "SIGNAL",
      "decimals": 18,
      "chainId": 137,
      "tags": ["underlying"]
    },
    {
      "address": "0x7f078f02a77e91e67ee592faed23d1cfcb390a60",
      "name": "Super Crosschain IOTX ",
      "symbol": "CIOTXx",
      "decimals": 18,
      "chainId": 137,
      "extensions": {
        "superTokenInfo": {
          "type": "Wrapper",
          "underlyingTokenAddress": "0x300211def2a644b036a9bdd3e58159bb2074d388"
        }
      },
      "logoURI": "https://raw.githubusercontent.com/superfluid-finance/assets/master/public/tokens/ciotx/icon.svg",
      "tags": ["supertoken", "tier_b"]
    },
    {
      "address": "0x300211def2a644b036a9bdd3e58159bb2074d388",
      "name": "Crosschain IOTX",
      "symbol": "CIOTX",
      "decimals": 18,
      "chainId": 137,
      "logoURI": "https://raw.githubusercontent.com/superfluid-finance/assets/master/public/tokens/ciotx/icon.svg",
      "tags": ["underlying"]
    },
    {
      "address": "0x8c9eada20fed455ae2a8f002a76dffe279a9d737",
      "name": "Super jXOF",
      "symbol": "jXOFx",
      "decimals": 18,
      "chainId": 137,
      "extensions": {
        "superTokenInfo": {
          "type": "Wrapper",
          "underlyingTokenAddress": "0x4a1e068bc23faec08a5817a2a58258e3378d36f0"
        }
      },
      "tags": ["supertoken", "tier_b"]
    },
    {
      "address": "0x4a1e068bc23faec08a5817a2a58258e3378d36f0",
      "name": "Jarvis Synthetic Franc CFA (UEMOA)",
      "symbol": "jXOF",
      "decimals": 18,
      "chainId": 137,
      "tags": ["underlying"]
    },
    {
      "address": "0x8ef4f0c0753048a39b4bc4eb3f545fdae00618b7",
      "name": "Super stake dao Curve.fi amDAI/amUSDC/a",
      "symbol": "sdam3CRVx",
      "decimals": 18,
      "chainId": 137,
      "extensions": {
        "superTokenInfo": {
          "type": "Wrapper",
          "underlyingTokenAddress": "0x7d60f21072b585351dfd5e8b17109458d97ec120"
        }
      },
      "logoURI": "https://raw.githubusercontent.com/superfluid-finance/assets/master/public/tokens/sdam3crv/icon.svg",
      "tags": ["supertoken", "tier_b"]
    },
    {
      "address": "0x7d60f21072b585351dfd5e8b17109458d97ec120",
      "name": "stake dao Curve.fi amDAI/amUSDC/amUSDT",
      "symbol": "sdam3CRV",
      "decimals": 18,
      "chainId": 137,
      "logoURI": "https://raw.githubusercontent.com/superfluid-finance/assets/master/public/tokens/sdam3crv/icon.svg",
      "tags": ["underlying"]
    },
    {
      "address": "0x9308a7116106269eb11834df494efd00d244cf8e",
      "name": "Astro Gold Lite",
      "symbol": "ALITE",
      "decimals": 18,
      "chainId": 137,
      "extensions": {
        "superTokenInfo": {
          "type": "Pure"
        }
      },
      "logoURI": "https://raw.githubusercontent.com/superfluid-finance/assets/master/public/tokens/alite/icon.svg",
      "tags": ["supertoken", "tier_b"]
    },
    {
      "address": "0x9556b40e816e2890fdaffb2ffd47f6493f240781",
      "name": "Super Kitty Party Reward Token (PoS)",
      "symbol": "KPTx",
      "decimals": 18,
      "chainId": 137,
      "extensions": {
        "superTokenInfo": {
          "type": "Wrapper",
          "underlyingTokenAddress": "0x7d369731e3d7f86417aa86ef4be26e309080bd2f"
        }
      },
      "logoURI": "https://raw.githubusercontent.com/superfluid-finance/assets/master/public/tokens/kpt/icon.svg",
      "tags": ["supertoken", "tier_b"]
    },
    {
      "address": "0x7d369731e3d7f86417aa86ef4be26e309080bd2f",
      "name": "Kitty Party Reward Token (PoS)",
      "symbol": "KPT",
      "decimals": 18,
      "chainId": 137,
      "logoURI": "https://raw.githubusercontent.com/superfluid-finance/assets/master/public/tokens/kpt/icon.svg",
      "tags": ["underlying"]
    },
    {
      "address": "0x96eac3913bab431c28895f02cf5c56ad2dab8439",
      "name": "Super Curve DAO Token",
      "symbol": "CRVx",
      "decimals": 18,
      "chainId": 137,
      "extensions": {
        "superTokenInfo": {
          "type": "Wrapper",
          "underlyingTokenAddress": "0x172370d5cd63279efa6d502dab29171933a610af"
        }
      },
      "logoURI": "https://raw.githubusercontent.com/superfluid-finance/assets/master/public/tokens/crv/icon.png",
      "tags": ["supertoken", "tier_b"]
    },
    {
      "address": "0x172370d5cd63279efa6d502dab29171933a610af",
      "name": "CRV (PoS)",
      "symbol": "CRV",
      "decimals": 18,
      "chainId": 137,
      "logoURI": "https://raw.githubusercontent.com/superfluid-finance/assets/master/public/tokens/crv/icon.png",
      "tags": ["underlying"]
    },
    {
      "address": "0x992446b88a7e62c7235bd88108f44543c1887c1f",
      "name": "MAI (miMATIC)",
      "symbol": "MAIx",
      "decimals": 18,
      "chainId": 137,
      "extensions": {
        "superTokenInfo": {
          "type": "Wrapper",
          "underlyingTokenAddress": "0xa3fa99a148fa48d14ed51d610c367c61876997f1"
        }
      },
      "logoURI": "https://raw.githubusercontent.com/superfluid-finance/assets/master/public/tokens/mimatic/icon.svg",
      "tags": ["supertoken", "tier_b"]
    },
    {
      "address": "0xa3fa99a148fa48d14ed51d610c367c61876997f1",
      "name": "miMATIC",
      "symbol": "miMATIC",
      "decimals": 18,
      "chainId": 137,
      "logoURI": "https://raw.githubusercontent.com/superfluid-finance/assets/master/public/tokens/mimatic/icon.svg",
      "tags": ["underlying"]
    },
    {
      "address": "0xa1bd23b582c12c22e5e264a0a69847ca0ed9f2b0",
      "name": "Super ChainLink Token",
      "symbol": "LINKx",
      "decimals": 18,
      "chainId": 137,
      "extensions": {
        "superTokenInfo": {
          "type": "Wrapper",
          "underlyingTokenAddress": "0x53e0bca35ec356bd5dddfebbd1fc0fd03fabad39"
        }
      },
      "logoURI": "https://raw.githubusercontent.com/superfluid-finance/assets/master/public/tokens/link/icon.png",
      "tags": ["supertoken", "tier_b"]
    },
    {
      "address": "0x53e0bca35ec356bd5dddfebbd1fc0fd03fabad39",
      "name": "ChainLink Token",
      "symbol": "LINK",
      "decimals": 18,
      "chainId": 137,
      "logoURI": "https://raw.githubusercontent.com/superfluid-finance/assets/master/public/tokens/link/icon.png",
      "tags": ["underlying"]
    },
    {
      "address": "0xab0b048e8b60eb9e8c7a2d46634326143393f2ea",
      "name": "Super mUSD",
      "symbol": "mUSDx",
      "decimals": 18,
      "chainId": 137,
      "extensions": {
        "superTokenInfo": {
          "type": "Wrapper",
          "underlyingTokenAddress": "0xe840b73e5287865eec17d250bfb1536704b43b21"
        }
      },
      "logoURI": "https://raw.githubusercontent.com/superfluid-finance/assets/master/public/tokens/mstable-usd-polygon-pos/icon.png",
      "tags": ["supertoken", "tier_b"]
    },
    {
      "address": "0xe840b73e5287865eec17d250bfb1536704b43b21",
      "name": "mUSD",
      "symbol": "mStableUSD(PolygonP",
      "decimals": 18,
      "chainId": 137,
      "logoURI": "https://raw.githubusercontent.com/superfluid-finance/assets/master/public/tokens/mstable-usd-polygon-pos/icon.png",
      "tags": ["underlying"]
    },
    {
      "address": "0xad0ffbb4e45c42a45a6206383ce2adf9102cdcb9",
      "name": "Super jPHP",
      "symbol": "jPHPx",
      "decimals": 18,
      "chainId": 137,
      "extensions": {
        "superTokenInfo": {
          "type": "Wrapper",
          "underlyingTokenAddress": "0x486880fb16408b47f928f472f57bec55ac6089d1"
        }
      },
      "logoURI": "https://raw.githubusercontent.com/superfluid-finance/assets/master/public/tokens/jphp/icon.png",
      "tags": ["supertoken", "tier_b"]
    },
    {
      "address": "0x486880fb16408b47f928f472f57bec55ac6089d1",
      "name": "Jarvis Synthetic Philippine Peso",
      "symbol": "jPHP",
      "decimals": 18,
      "chainId": 137,
      "logoURI": "https://raw.githubusercontent.com/superfluid-finance/assets/master/public/tokens/jphp/icon.png",
      "tags": ["underlying"]
    },
    {
      "address": "0xb0512060ee623a656da1f25686743474228ba0e6",
      "name": "Super APWine Token (PoS)",
      "symbol": "APWx",
      "decimals": 18,
      "chainId": 137,
      "extensions": {
        "superTokenInfo": {
          "type": "Wrapper",
          "underlyingTokenAddress": "0x6c0ab120dbd11ba701aff6748568311668f63fe0"
        }
      },
      "logoURI": "https://raw.githubusercontent.com/superfluid-finance/assets/master/public/tokens/apw/icon.svg",
      "tags": ["supertoken", "tier_b"]
    },
    {
      "address": "0x6c0ab120dbd11ba701aff6748568311668f63fe0",
      "name": "APWine Token (PoS)",
      "symbol": "APW",
      "decimals": 18,
      "chainId": 137,
      "logoURI": "https://raw.githubusercontent.com/superfluid-finance/assets/master/public/tokens/apw/icon.svg",
      "tags": ["underlying"]
    },
    {
      "address": "0xb63e38d21b31719e6df314d3d2c351df0d4a9162",
      "name": "Super Idle (PoS)",
      "symbol": "IDLEx",
      "decimals": 18,
      "chainId": 137,
      "extensions": {
        "superTokenInfo": {
          "type": "Wrapper",
          "underlyingTokenAddress": "0xc25351811983818c9fe6d8c580531819c8ade90f"
        }
      },
      "logoURI": "https://raw.githubusercontent.com/superfluid-finance/assets/master/public/tokens/idle/icon.png",
      "tags": ["supertoken", "tier_b"]
    },
    {
      "address": "0xc25351811983818c9fe6d8c580531819c8ade90f",
      "name": "Idle (PoS)",
      "symbol": "IDLE",
      "decimals": 18,
      "chainId": 137,
      "logoURI": "https://raw.githubusercontent.com/superfluid-finance/assets/master/public/tokens/idle/icon.png",
      "tags": ["underlying"]
    },
    {
      "address": "0xb683fb34a77c06931ba62d804252d1f60596a36a",
      "name": "Super Spork",
      "symbol": "SPORKx",
      "decimals": 18,
      "chainId": 137,
      "extensions": {
        "superTokenInfo": {
          "type": "Wrapper",
          "underlyingTokenAddress": "0x9ca6a77c8b38159fd2da9bd25bc3e259c33f5e39"
        }
      },
      "logoURI": "https://raw.githubusercontent.com/superfluid-finance/assets/master/public/tokens/spork/icon.png",
      "tags": ["supertoken", "tier_b"]
    },
    {
      "address": "0x9ca6a77c8b38159fd2da9bd25bc3e259c33f5e39",
      "name": "The SporkDAO Token (PoS)",
      "symbol": "SPORK",
      "decimals": 18,
      "chainId": 137,
      "logoURI": "https://raw.githubusercontent.com/superfluid-finance/assets/master/public/tokens/spork/icon.png",
      "tags": ["underlying"]
    },
    {
      "address": "0xbd80cfa9d93a87d1bb895f810ea348e496611cd4",
      "name": "Own a fraction",
      "symbol": "FRACTION",
      "decimals": 18,
      "chainId": 137,
      "extensions": {
        "superTokenInfo": {
          "type": "Pure"
        }
      },
      "logoURI": "https://raw.githubusercontent.com/superfluid-finance/assets/master/public/tokens/fraction/icon.svg",
      "tags": ["supertoken", "tier_b"]
    },
    {
      "address": "0xc0b2983a17573660053beeed6fdb1053107cf387",
      "name": "Minerva Wallet SuperToken",
      "symbol": "MIVA",
      "decimals": 18,
      "chainId": 137,
      "extensions": {
        "superTokenInfo": {
          "type": "Pure"
        }
      },
      "logoURI": "https://raw.githubusercontent.com/superfluid-finance/assets/master/public/tokens/miva/icon.svg",
      "tags": ["supertoken", "tier_b"]
    },
    {
      "address": "0xcae73e9eee8a01b8b7f94b59133e3821f21470ab",
      "name": "Stacker Ventures Token",
      "symbol": "STACKx",
      "decimals": 18,
      "chainId": 137,
      "extensions": {
        "superTokenInfo": {
          "type": "Wrapper",
          "underlyingTokenAddress": "0xccbe9b810d6574701d324fd6dbe0a1b68f9d5bf7"
        }
      },
      "logoURI": "https://raw.githubusercontent.com/superfluid-finance/assets/master/public/tokens/stack/icon.svg",
      "tags": ["supertoken", "tier_b"]
    },
    {
      "address": "0xccbe9b810d6574701d324fd6dbe0a1b68f9d5bf7",
      "name": "Stacker Ventures Token (PoS)",
      "symbol": "STACK",
      "decimals": 18,
      "chainId": 137,
      "logoURI": "https://raw.githubusercontent.com/superfluid-finance/assets/master/public/tokens/stack/icon.svg",
      "tags": ["underlying"]
    },
    {
      "address": "0xcb5676568febb4e4f0dca9407318836e7a973183",
      "name": "Super Instadapp",
      "symbol": "INSTx",
      "decimals": 18,
      "chainId": 137,
      "extensions": {
        "superTokenInfo": {
          "type": "Wrapper",
          "underlyingTokenAddress": "0xf50d05a1402d0adafa880d36050736f9f6ee7dee"
        }
      },
      "logoURI": "https://raw.githubusercontent.com/superfluid-finance/assets/master/public/tokens/inst/icon.svg",
      "tags": ["supertoken", "tier_b"]
    },
    {
      "address": "0xf50d05a1402d0adafa880d36050736f9f6ee7dee",
      "name": "Instadapp (PoS)",
      "symbol": "INST",
      "decimals": 18,
      "chainId": 137,
      "logoURI": "https://raw.githubusercontent.com/superfluid-finance/assets/master/public/tokens/inst/icon.svg",
      "tags": ["underlying"]
    },
    {
      "address": "0xcf75b3b2d305690f4d70d8aeaa36e9f7813e806d",
      "name": "Super jXAF",
      "symbol": "jXAFx",
      "decimals": 18,
      "chainId": 137,
      "extensions": {
        "superTokenInfo": {
          "type": "Wrapper",
          "underlyingTokenAddress": "0x98fab5d1366de24f152ea683a1f23338351c47ea"
        }
      },
      "tags": ["supertoken", "tier_b"]
    },
    {
      "address": "0x98fab5d1366de24f152ea683a1f23338351c47ea",
      "name": "Jarvis Synthetic Franc CFA (CEMAC)",
      "symbol": "jXAF",
      "decimals": 18,
      "chainId": 137,
      "tags": ["underlying"]
    },
    {
      "address": "0xd98a3eabb78a759868d5a35677ffa99a78f33ec7",
      "name": "Super Artizen Token",
      "symbol": "ARTx",
      "decimals": 18,
      "chainId": 137,
      "extensions": {
        "superTokenInfo": {
          "type": "Wrapper",
          "underlyingTokenAddress": "0xd7f3aac7557c213b035c19bd89bd693396acccd6"
        }
      },
      "logoURI": "https://raw.githubusercontent.com/superfluid-finance/assets/master/public/tokens/art/icon.svg",
      "tags": ["supertoken", "tier_b"]
    },
    {
      "address": "0xd7f3aac7557c213b035c19bd89bd693396acccd6",
      "name": "Artizen Token",
      "symbol": "ART",
      "decimals": 18,
      "chainId": 137,
      "logoURI": "https://raw.githubusercontent.com/superfluid-finance/assets/master/public/tokens/art/icon.svg",
      "tags": ["underlying"]
    },
    {
      "address": "0xe127d2d7b2ce51130429e32d22d908e8d96a3247",
      "name": "Super jSGD",
      "symbol": "jSGDx",
      "decimals": 18,
      "chainId": 137,
      "extensions": {
        "superTokenInfo": {
          "type": "Wrapper",
          "underlyingTokenAddress": "0xa926db7a4cc0cb1736d5ac60495ca8eb7214b503"
        }
      },
      "tags": ["supertoken", "tier_b"]
    },
    {
      "address": "0xa926db7a4cc0cb1736d5ac60495ca8eb7214b503",
      "name": "Jarvis Synthetic Singapore Dollar",
      "symbol": "jSGD",
      "decimals": 18,
      "chainId": 137,
      "tags": ["underlying"]
    },
    {
      "address": "0xe199f1b01dd3e8a1c43b62279feb20547a2eb3ef",
      "name": "Streaming IbAlluo EUR",
      "symbol": "StIbAlluoEUR",
      "decimals": 18,
      "chainId": 137,
      "extensions": {
        "superTokenInfo": {
          "type": "Wrapper",
          "underlyingTokenAddress": "0xc9d8556645853c465d1d5e7d2c81a0031f0b8a92"
        }
      },
      "logoURI": "https://raw.githubusercontent.com/superfluid-finance/assets/master/public/tokens/iballuoeur/icon.svg",
      "tags": ["supertoken", "tier_b"]
    },
    {
      "address": "0xc9d8556645853c465d1d5e7d2c81a0031f0b8a92",
      "name": "Interest Bearing Alluo EUR",
      "symbol": "IbAlluoEUR",
      "decimals": 18,
      "chainId": 137,
      "logoURI": "https://raw.githubusercontent.com/superfluid-finance/assets/master/public/tokens/iballuoeur/icon.svg",
      "tags": ["underlying"]
    },
    {
      "address": "0xe1c042c91fa08875323e57978c9b9fb413297cf2",
      "name": "Super IoTeX",
      "symbol": "IOTXx",
      "decimals": 18,
      "chainId": 137,
      "extensions": {
        "superTokenInfo": {
          "type": "Wrapper",
          "underlyingTokenAddress": "0xf6372cdb9c1d3674e83842e3800f2a62ac9f3c66"
        }
      },
      "logoURI": "https://raw.githubusercontent.com/superfluid-finance/assets/master/public/tokens/iotx/icon.svg",
      "tags": ["supertoken", "tier_b"]
    },
    {
      "address": "0xf6372cdb9c1d3674e83842e3800f2a62ac9f3c66",
      "name": "IoTeX Network (PoS)",
      "symbol": "IOTX",
      "decimals": 18,
      "chainId": 137,
      "logoURI": "https://raw.githubusercontent.com/superfluid-finance/assets/master/public/tokens/iotx/icon.svg",
      "tags": ["underlying"]
    },
    {
      "address": "0xe1ca10e6a10c0f72b74df6b7339912babfb1f8b5",
      "name": "superQI",
      "symbol": "QIx",
      "decimals": 18,
      "chainId": 137,
      "extensions": {
        "superTokenInfo": {
          "type": "Wrapper",
          "underlyingTokenAddress": "0x580a84c73811e1839f75d86d75d88cca0c241ff4"
        }
      },
      "logoURI": "https://raw.githubusercontent.com/superfluid-finance/assets/master/public/tokens/qi/icon.svg",
      "tags": ["supertoken", "tier_b"]
    },
    {
      "address": "0x580a84c73811e1839f75d86d75d88cca0c241ff4",
      "name": "Qi Dao",
      "symbol": "QI",
      "decimals": 18,
      "chainId": 137,
      "logoURI": "https://raw.githubusercontent.com/superfluid-finance/assets/master/public/tokens/qi/icon.svg",
      "tags": ["underlying"]
    },
    {
      "address": "0xe2d04ab74eed9627c828b3fc10e5fc96fae70348",
      "name": "Super jCHF",
      "symbol": "jCHFx",
      "decimals": 18,
      "chainId": 137,
      "extensions": {
        "superTokenInfo": {
          "type": "Wrapper",
          "underlyingTokenAddress": "0xbd1463f02f61676d53fd183c2b19282bff93d099"
        }
      },
      "logoURI": "https://raw.githubusercontent.com/superfluid-finance/assets/master/public/tokens/jchf/icon.svg",
      "tags": ["supertoken", "tier_b"]
    },
    {
      "address": "0xbd1463f02f61676d53fd183c2b19282bff93d099",
      "name": "Jarvis Synthetic Swiss Franc",
      "symbol": "jCHF",
      "decimals": 18,
      "chainId": 137,
      "logoURI": "https://raw.githubusercontent.com/superfluid-finance/assets/master/public/tokens/jchf/icon.svg",
      "tags": ["underlying"]
    },
    {
      "address": "0xe9e759b969b991f2bfae84308385405b9ab01541",
      "name": "Streaming IbAlluo USD",
      "symbol": "StIbAlluoUSD",
      "decimals": 18,
      "chainId": 137,
      "extensions": {
        "superTokenInfo": {
          "type": "Wrapper",
          "underlyingTokenAddress": "0xc2dbaaea2efa47ebda3e572aa0e55b742e408bf6"
        }
      },
      "logoURI": "https://raw.githubusercontent.com/superfluid-finance/assets/master/public/tokens/iballuousd/icon.svg",
      "tags": ["supertoken", "tier_b"]
    },
    {
      "address": "0xc2dbaaea2efa47ebda3e572aa0e55b742e408bf6",
      "name": "Interest Bearing Alluo USD",
      "symbol": "IbAlluoUSD",
      "decimals": 18,
      "chainId": 137,
      "logoURI": "https://raw.githubusercontent.com/superfluid-finance/assets/master/public/tokens/iballuousd/icon.svg",
      "tags": ["underlying"]
    },
    {
      "address": "0xeb5748f9798b11af79f892f344f585e3a88aa784",
      "name": "Super IdleWETH [Best yield]",
      "symbol": "idleWETHx",
      "decimals": 18,
      "chainId": 137,
      "extensions": {
        "superTokenInfo": {
          "type": "Wrapper",
          "underlyingTokenAddress": "0xfda25d931258df948ffecb66b5518299df6527c4"
        }
      },
      "logoURI": "https://raw.githubusercontent.com/superfluid-finance/assets/master/public/tokens/idlewethyield/icon.svg",
      "tags": ["supertoken", "tier_b"]
    },
    {
      "address": "0xfda25d931258df948ffecb66b5518299df6527c4",
      "name": "IdleWETH [Best yield]",
      "symbol": "idleWETHYield",
      "decimals": 18,
      "chainId": 137,
      "logoURI": "https://raw.githubusercontent.com/superfluid-finance/assets/master/public/tokens/idlewethyield/icon.svg",
      "tags": ["underlying"]
    },
    {
      "address": "0xfac83774854237b6e31c4b051b91015e403956d3",
      "name": "Astro Gold",
      "symbol": "AGOLD",
      "decimals": 18,
      "chainId": 137,
      "extensions": {
        "superTokenInfo": {
          "type": "Wrapper",
          "underlyingTokenAddress": "0xe06bd4f5aac8d0aa337d13ec88db6defc6eaeefe"
        }
      },
      "logoURI": "https://raw.githubusercontent.com/superfluid-finance/assets/master/public/tokens/agold/icon.svg",
      "tags": ["supertoken", "tier_b"]
    },
    {
      "address": "0xe06bd4f5aac8d0aa337d13ec88db6defc6eaeefe",
      "name": "PlanetIX",
      "symbol": "IXT",
      "decimals": 18,
      "chainId": 137,
      "logoURI": "https://raw.githubusercontent.com/superfluid-finance/assets/master/public/tokens/agold/icon.svg",
      "tags": ["underlying"]
    },
    {
      "address": "0xfbb291570de4b87353b1e0f586df97a1ed856470",
      "name": "Super JPY Coin (PoS)",
      "symbol": "JPYCx",
      "decimals": 18,
      "chainId": 137,
      "extensions": {
        "superTokenInfo": {
          "type": "Wrapper",
          "underlyingTokenAddress": "0x6ae7dfc73e0dde2aa99ac063dcf7e8a63265108c"
        }
      },
      "logoURI": "https://raw.githubusercontent.com/superfluid-finance/assets/master/public/tokens/jpyc/icon.svg",
      "tags": ["supertoken", "tier_b"]
    },
    {
      "address": "0x6ae7dfc73e0dde2aa99ac063dcf7e8a63265108c",
      "name": "JPY Coin (PoS)",
      "symbol": "JPYC",
      "decimals": 18,
      "chainId": 137,
      "logoURI": "https://raw.githubusercontent.com/superfluid-finance/assets/master/public/tokens/jpyc/icon.svg",
      "tags": ["underlying"]
    },
    {
      "address": "0xfd0577c4707367ff9b637f219388919d3be37592",
      "name": "Super Gains Network",
      "symbol": "GNSx",
      "decimals": 18,
      "chainId": 137,
      "extensions": {
        "superTokenInfo": {
          "type": "Wrapper",
          "underlyingTokenAddress": "0xe5417af564e4bfda1c483642db72007871397896"
        }
      },
      "logoURI": "https://raw.githubusercontent.com/superfluid-finance/assets/master/public/tokens/gns/icon.png",
      "tags": ["supertoken", "tier_b"]
    },
    {
      "address": "0xe5417af564e4bfda1c483642db72007871397896",
      "name": "Gains Network",
      "symbol": "GNS",
      "decimals": 18,
      "chainId": 137,
      "logoURI": "https://raw.githubusercontent.com/superfluid-finance/assets/master/public/tokens/gns/icon.png",
      "tags": ["underlying"]
    }
  ],
  "tags": {
    "supertoken": {
      "name": "SuperToken",
      "description": "This is a supertoken, learn more from the extensions."
    },
    "underlying": {
      "name": "Underlying Token",
      "description": "This is an underlying token, of a supertoken."
    },
    "testnet": {
      "name": "Testnet",
      "description": "This is a testnet token."
    },
    "tier_a": {
      "name": "Solvency Tier A",
      "description": "This is a Tier A token based on Solvency: Native Asset, or Stablecoin."
    },
    "tier_b": {
      "name": "Solvency Tier B",
      "description": "This is a Tier B token based on Solvency: Tied to a project or company, and has value, or utility."
    },
    "tier_c": {
      "name": "Solvency Tier C",
      "description": "This is a Tier C token based on Solvency: Not qualifying for Solvency Tier A or B."
    }
  }
}
